{"indicators":[{"id":"SPX","name":"S&P 500","value":7173.91,"change":8.83,"unit":"Index","updated":"04/27/26 EDT","source":"CNBC"},{"id":"IXIC","name":"Nasdaq","value":24887.1,"change":50.501,"unit":"Index","updated":"04/27/26 EDT","source":"CNBC"},{"id":"DXY","name":"DXY (US Dollar)","value":98.754,"change":0.258,"unit":"Index","updated":"5:41 AM EDT","source":"CNBC"},{"id":"US10Y","name":"US 10Y Treasury","value":4.358,"change":0.022,"unit":"%","updated":"5:39 AM EDT","source":"CNBC"},{"id":"US2Y","name":"US 2Y Treasury","value":3.822,"change":0.017,"unit":"%","updated":"5:40 AM EDT","source":"CNBC"},{"id":"VIX","name":"VIX","value":18.34,"change":0.32,"unit":"Index","updated":"5:41 AM EDT","source":"CNBC"},{"id":"GOLD","name":"Gold","value":4629.6,"change":-64.1,"unit":"USD","updated":"5:31 AM EDT","source":"CNBC"},{"id":"DFF","name":"Fed Funds Rate","value":3.64,"change":0.0,"unit":"%","updated":"2026-04-24","source":"FRED"}],"generated":"2026-04-28T09:41:06.292833+00:00"}