{"indicators": [{"id": "SPX", "name": "S&P 500", "value": 7365.12, "change": 105.9, "unit": "Index", "updated": "4:41 PM EDT", "source": "CNBC"}, {"id": "IXIC", "name": "Nasdaq", "value": 25838.943, "change": 512.817, "unit": "Index", "updated": "5:15 PM EDT", "source": "CNBC"}, {"id": "DXY", "name": "DXY (US Dollar)", "value": 97.929, "change": -0.094, "unit": "Index", "updated": "10:02 PM EDT", "source": "CNBC"}, {"id": "US10Y", "name": "US 10Y Treasury", "value": 4.344, "change": -0.01, "unit": "%", "updated": "10:02 PM EDT", "source": "CNBC"}, {"id": "US2Y", "name": "US 2Y Treasury", "value": 3.866, "change": -0.006, "unit": "%", "updated": "9:58 PM EDT", "source": "CNBC"}, {"id": "VIX", "name": "VIX", "value": 17.39, "change": 0.01, "unit": "Index", "updated": "4:15 PM EDT", "source": "CNBC"}, {"id": "GOLD", "name": "Gold", "value": 4729.0, "change": 34.7, "unit": "USD", "updated": "9:52 PM EDT", "source": "CNBC"}, {"id": "DFF", "name": "Fed Funds Rate", "value": 3.64, "change": 0.0, "unit": "%", "updated": "2026-05-05", "source": "FRED"}], "generated": "2026-05-07T02:02:30.770051+00:00"}