{"indicators":[{"id":"SPX","name":"S&P 500","value":6824.66,"change":41.85,"unit":"Index","updated":"04/09/26 EDT","source":"CNBC"},{"id":"IXIC","name":"Nasdaq","value":22822.417,"change":187.422,"unit":"Index","updated":"04/09/26 EDT","source":"CNBC"},{"id":"DXY","name":"DXY (US Dollar)","value":98.815,"change":null,"unit":"Index","updated":"5:22 AM EDT","source":"CNBC"},{"id":"US10Y","name":"US 10Y Treasury","value":4.295,"change":0.002,"unit":"%","updated":"5:22 AM EDT","source":"CNBC"},{"id":"US2Y","name":"US 2Y Treasury","value":3.789,"change":0.006,"unit":"%","updated":"5:22 AM EDT","source":"CNBC"},{"id":"VIX","name":"VIX","value":19.44,"change":-0.05,"unit":"Index","updated":"5:22 AM EDT","source":"CNBC"},{"id":"GOLD","name":"Gold","value":4765.4,"change":-52.6,"unit":"USD","updated":"5:12 AM EDT","source":"CNBC"},{"id":"DFF","name":"Fed Funds Rate","value":3.64,"change":0.0,"unit":"%","updated":"2026-04-08","source":"FRED"}],"generated":"2026-04-10T09:22:39.358236+00:00"}