{"btc_price": 80799, "btc_change_24h": 0.78958, "eth_price": 2329.14, "eth_change_24h": 0.95184, "fear_greed_index": 38, "fear_greed_label": "Fear", "total_market_cap_b": 2775.6, "btc_dominance": 58.3, "total_volume_24h_b": 65.4, "top_gainers": [{"symbol": "AURAUSDT", "name": "aura", "image": "https://coin-images.coingecko.com/coins/images/38376/large/aura_logo_200x200-01-01.png?1751114135", "price": 0.03913656, "change_24h": 293.37379, "volume_24h": 38437118}, {"symbol": "INXUSDT", "name": "Infinex", "image": "https://coin-images.coingecko.com/coins/images/70868/large/infinex.png?1764322875", "price": 0.01565955, "change_24h": 59.97294, "volume_24h": 20619801}, {"symbol": "OMUSDT", "name": "MANTRA [Old]", "image": "https://coin-images.coingecko.com/coins/images/12151/large/OM_Token.png?1696511991", "price": 0.01113982, "change_24h": 40.88136, "volume_24h": 5460.18}, {"symbol": "BILLUSDT", "name": "Billions Network", "image": "https://coin-images.coingecko.com/coins/images/68464/large/billions.png?1755828007", "price": 0.120857, "change_24h": 37.45114, "volume_24h": 525938978}, {"symbol": "QUSDT", "name": "Quack AI", "image": "https://coin-images.coingecko.com/coins/images/68793/large/quack_ai.png?1756615808", "price": 0.01567972, "change_24h": 33.11613, "volume_24h": 15884291}, {"symbol": "OREUSDT", "name": "ORE", "image": "https://coin-images.coingecko.com/coins/images/36854/large/IMG_7340.png?1712633659", "price": 93.61, "change_24h": 29.18318, "volume_24h": 2744016}, {"symbol": "SAHARAUSDT", "name": "Sahara AI", "image": "https://coin-images.coingecko.com/coins/images/66681/large/Token_Logo_3x.png?1750362133", "price": 0.0388244, "change_24h": 28.32897, "volume_24h": 319574949}, {"symbol": "MHORSEUSDT", "name": "MEME HORSE", "image": "https://coin-images.coingecko.com/coins/images/102171984/large/1000322552.png?1770837497", "price": 0.057073, "change_24h": 28.01434, "volume_24h": 1028968}, {"symbol": "ZEREBROUSDT", "name": "Zerebro", "image": "https://coin-images.coingecko.com/coins/images/51289/large/zerebro_2.png?1730588883", "price": 0.04868467, "change_24h": 24.76797, "volume_24h": 17539317}, {"symbol": "BASUSDT", "name": "BNB Attestation Service", "image": "https://coin-images.coingecko.com/coins/images/67419/large/bas.jpg?1752736026", "price": 0.020453, "change_24h": 23.43982, "volume_24h": 11216042}], "top_losers": [{"symbol": "OPENUSDT", "name": "OpenLedger", "image": "https://coin-images.coingecko.com/coins/images/67482/large/open.png?1756547643", "price": 0.197615, "change_24h": -15.44043, "volume_24h": 40115582}, {"symbol": "CARDSUSDT", "name": "Collector Crypt", "image": "https://coin-images.coingecko.com/coins/images/68728/large/cards-logo.jpeg?1756534539", "price": 0.12254, "change_24h": -14.48055, "volume_24h": 4270762}, {"symbol": "XPUSDT", "name": "Xphere", "image": "https://coin-images.coingecko.com/coins/images/54874/large/oAapmKlz_400x400.png?1742236858", "price": 0.01994793, "change_24h": -14.23503, "volume_24h": 727011}, {"symbol": "TRIAUSDT", "name": "TRIA", "image": "https://coin-images.coingecko.com/coins/images/102171854/large/Tria_-_Black_symbol_%281%29.png?1770111654", "price": 0.03770548, "change_24h": -13.36665, "volume_24h": 9840279}, {"symbol": "STONUSDT", "name": "STON", "image": "https://coin-images.coingecko.com/coins/images/31233/large/STON.jpg?1696530059", "price": 0.775736, "change_24h": -11.247, "volume_24h": 135432}, {"symbol": "AUKIUSDT", "name": "Auki", "image": "https://coin-images.coingecko.com/coins/images/39811/large/COINGECKO-200-x-200_%281%29.png?1724166209", "price": 0.00689656, "change_24h": -11.06579, "volume_24h": 112921}, {"symbol": "SN3USDT", "name": "τemplar", "image": "https://coin-images.coingecko.com/coins/images/66334/large/sn3.png?1749237576", "price": 8.64, "change_24h": -10.5593, "volume_24h": 4224556}, {"symbol": "RSCUSDT", "name": "ResearchCoin", "image": "https://coin-images.coingecko.com/coins/images/28146/large/RH_BOTTLE_CLEAN_Aug_2024_1.png?1732742001", "price": 0.144667, "change_24h": -10.17465, "volume_24h": 1063931}, {"symbol": "STRKUSDT", "name": "Starknet", "image": "https://coin-images.coingecko.com/coins/images/26433/large/starknet.png?1696525507", "price": 0.052796, "change_24h": -9.94995, "volume_24h": 188885068}, {"symbol": "CHIPUSDT", "name": "USD.AI", "image": "https://coin-images.coingecko.com/coins/images/102171777/large/CHIP_Token_Logo_Large.png?1776777444", "price": 0.066721, "change_24h": -9.1983, "volume_24h": 286375397}], "extreme_funding": [], "generated": "2026-05-09T20:54:31.164585+00:00"}