{"btc_price": 80623, "btc_change_24h": -1.48688, "eth_price": 2286.24, "eth_change_24h": -2.36595, "fear_greed_index": 49, "fear_greed_label": "Neutral", "total_market_cap_b": 2771.8, "btc_dominance": 58.3, "total_volume_24h_b": 91.5, "top_gainers": [{"symbol": "BILLUSDT", "name": "Billions Network", "image": "https://coin-images.coingecko.com/coins/images/68464/large/billions.png?1755828007", "price": 0.19929, "change_24h": 41.4578, "volume_24h": 275305248}, {"symbol": "TRUTHUSDT", "name": "Swarm Network", "image": "https://coin-images.coingecko.com/coins/images/69599/large/truth.png?1759208403", "price": 0.01878061, "change_24h": 29.15925, "volume_24h": 8768585}, {"symbol": "TELUSDT", "name": "Telcoin", "image": "https://coin-images.coingecko.com/coins/images/1899/large/tel.png?1696502892", "price": 0.0028367, "change_24h": 27.66879, "volume_24h": 9699022}, {"symbol": "PEAQUSDT", "name": "peaq", "image": "https://coin-images.coingecko.com/coins/images/51415/large/peaq-token-brand-icon_%281%29.png?1731122664", "price": 0.02237833, "change_24h": 27.01295, "volume_24h": 15989296}, {"symbol": "GUAUSDT", "name": "Superfortune", "image": "https://coin-images.coingecko.com/coins/images/70828/large/superfortune.png?1764058443", "price": 1.29, "change_24h": 25.79759, "volume_24h": 4209490}, {"symbol": "SKYAIUSDT", "name": "SkyAI", "image": "https://coin-images.coingecko.com/coins/images/55294/large/1.png?1745517593", "price": 0.562624, "change_24h": 21.6432, "volume_24h": 46483904}, {"symbol": "UPUSDT", "name": "Superform", "image": "https://coin-images.coingecko.com/coins/images/70945/large/superform.png?1764747920", "price": 0.152361, "change_24h": 21.48675, "volume_24h": 5888969}, {"symbol": "SAHARAUSDT", "name": "Sahara AI", "image": "https://coin-images.coingecko.com/coins/images/66681/large/Token_Logo_3x.png?1750362133", "price": 0.04394665, "change_24h": 20.33815, "volume_24h": 194419246}, {"symbol": "ESPORTSUSDT", "name": "Yooldo Games", "image": "https://coin-images.coingecko.com/coins/images/67430/large/symbol-esports.png?1770141653", "price": 0.558761, "change_24h": 20.287, "volume_24h": 33220206}, {"symbol": "GIGAUSDT", "name": "Gigachad", "image": "https://coin-images.coingecko.com/coins/images/34755/large/IMG_0015.png?1705957165", "price": 0.00573848, "change_24h": 19.46201, "volume_24h": 26945482}], "top_losers": [{"symbol": "OSMOUSDT", "name": "Osmosis", "image": "https://coin-images.coingecko.com/coins/images/16724/large/osmo.png?1696516298", "price": 0.059198, "change_24h": -28.01323, "volume_24h": 37723313}, {"symbol": "GALUSDT", "name": "GAL (migrated to Gravity - G)", "image": "https://coin-images.coingecko.com/coins/images/24530/large/galaxy.jpg?1696523708", "price": 0.260727, "change_24h": -23.62389, "volume_24h": 57.3}, {"symbol": "OCTUSDT", "name": "Octra", "image": "https://coin-images.coingecko.com/coins/images/71026/large/octra.png?1765330700", "price": 0.055936, "change_24h": -19.31654, "volume_24h": 792177}, {"symbol": "BTWUSDT", "name": "Bitway", "image": "https://coin-images.coingecko.com/coins/images/71205/large/bitway.png?1766388722", "price": 0.01431566, "change_24h": -17.73944, "volume_24h": 11985318}, {"symbol": "NOCKUSDT", "name": "Nockchain", "image": "https://coin-images.coingecko.com/coins/images/68474/large/GrCcG9N9_400x400.jpg?1755845184", "price": 0.02304208, "change_24h": -16.79079, "volume_24h": 2570555}, {"symbol": "KAIOUSDT", "name": "KAIO", "image": "https://coin-images.coingecko.com/coins/images/102172908/large/mzBp0v3p_400x400.png?1778125287", "price": 0.098326, "change_24h": -15.86719, "volume_24h": 12597400}, {"symbol": "UTYAUSDT", "name": "Utya", "image": "https://coin-images.coingecko.com/coins/images/37227/large/photo_2024-04-15_18.03.55.jpeg?1713776606", "price": 0.03067704, "change_24h": -15.0941, "volume_24h": 1523205}, {"symbol": "PLAYUSDT", "name": "PlaysOut", "image": "https://coin-images.coingecko.com/coins/images/67765/large/plays.jpg?1753786347", "price": 0.088744, "change_24h": -14.5318, "volume_24h": 5554843}, {"symbol": "TROLLUSDT", "name": "TROLL", "image": "https://coin-images.coingecko.com/coins/images/55282/large/Untitled_design.png?1777015928", "price": 0.104807, "change_24h": -14.25056, "volume_24h": 25006362}, {"symbol": "ALCHUSDT", "name": "Alchemist AI", "image": "https://coin-images.coingecko.com/coins/images/52302/large/small-logo.png?1733053544", "price": 0.085025, "change_24h": -13.95088, "volume_24h": 10127766}], "extreme_funding": [], "generated": "2026-05-12T22:17:53.856714+00:00"}